testpad/__init__.py
testpad_python-0.1.0.dist-info/METADATA
testpad_python-0.1.0.dist-info/WHEEL
testpad_python-0.1.0.dist-info/RECORD
